albania/__init__.py
albania/windows/__init__.py
albania/windows/ctk_input_dialog.py
albania/windows/ctk_tk.py
albania/windows/ctk_toplevel.py
albania/windows/widgets/__init__.py
albania/windows/widgets/ctk_button.py
albania/windows/widgets/ctk_checkbox.py
albania/windows/widgets/ctk_combobox.py
albania/windows/widgets/ctk_entry.py
albania/windows/widgets/ctk_frame.py
albania/windows/widgets/ctk_label.py
albania/windows/widgets/ctk_optionmenu.py
albania/windows/widgets/ctk_progressbar.py
albania/windows/widgets/ctk_radiobutton.py
albania/windows/widgets/ctk_scrollable_frame.py
albania/windows/widgets/ctk_scrollbar.py
albania/windows/widgets/ctk_segmented_button.py
albania/windows/widgets/ctk_slider.py
albania/windows/widgets/ctk_switch.py
albania/windows/widgets/ctk_tabview.py
albania/windows/widgets/ctk_textbox.py
albania/windows/widgets/appearance_mode/__init__.py
albania/windows/widgets/appearance_mode/appearance_mode_base_class.py
albania/windows/widgets/appearance_mode/appearance_mode_tracker.py
albania/windows/widgets/core_rendering/__init__.py
albania/windows/widgets/core_rendering/ctk_canvas.py
albania/windows/widgets/core_rendering/draw_engine.py
albania/windows/widgets/core_widget_classes/__init__.py
albania/windows/widgets/core_widget_classes/ctk_base_class.py
albania/windows/widgets/core_widget_classes/dropdown_menu.py
albania/windows/widgets/font/__init__.py
albania/windows/widgets/font/ctk_font.py
albania/windows/widgets/font/font_manager.py
albania/windows/widgets/image/__init__.py
albania/windows/widgets/image/ctk_image.py
albania/windows/widgets/scaling/__init__.py
albania/windows/widgets/scaling/scaling_base_class.py
albania/windows/widgets/scaling/scaling_tracker.py
albania/windows/widgets/theme/__init__.py
albania/windows/widgets/theme/theme_manager.py
albania/windows/widgets/utility/__init__.py
albania/windows/widgets/utility/utility_functions.py
albania-0.0.2.dist-info/LICENSE
albania-0.0.2.dist-info/METADATA
albania-0.0.2.dist-info/WHEEL
albania-0.0.2.dist-info/top_level.txt
albania-0.0.2.dist-info/RECORD
