Metadata-Version: 2.1
Name: albania
Version: 0.0.2
Summary: Albanian Utilities
Home-page: https://github.com/fat-mir/albania
Author: Albanian
Project-URL: Bug Tracker, https://github.com/fat-mir/albania
Classifier: Programming Language :: Python :: 3
Classifier: License :: OSI Approved :: MIT License
Classifier: Operating System :: OS Independent
Requires-Python: >=3.11
License-File: LICENSE
